Metadata-Version: 1.0
Name: pyls-mypy
Version: 0.1.1
Summary: Mypy linter for the Python Language Server for the Language Server Protocol
Home-page: https://github.com/tomv564/pyls-mypy
Author: Tom van Ommeren
Author-email: UNKNOWN
License: UNKNOWN
Platform: UNKNOWN
